xlconv/__init__.py
xlconv/main.py
xlconv/version.py
xlconv/xl_parser.py
xlconv-1.0.3.dist-info/LICENSE
xlconv-1.0.3.dist-info/METADATA
xlconv-1.0.3.dist-info/WHEEL
xlconv-1.0.3.dist-info/entry_points.txt
xlconv-1.0.3.dist-info/top_level.txt
xlconv-1.0.3.dist-info/RECORD
