Metadata-Version: 2.1
Name: xlconv
Version: 1.0.3
Summary: 一款转换工具，将excel转换为Json/Xml，支持各种数据类型，且数组和对象支持无限深度
Author: lujianwan
Author-email: lu_jiawan@163.com
Requires-Python: >=3.6
License-File: LICENSE
Requires-Dist: xlrd
Requires-Dist: dicttoxml
